{
    "basic_info": {
      "description_header": "Hi :)",
      "description": "👋 I'm Matteo Baldassin and i like programming, solve problems and always putting myself in competition",
      "section_name": {
        "about": "About",
        "projects": "Projects",
        "skills": "Skills",
        "experience": "Experience"
      }
    },
    "projects": [
      {
        "title": "Expenses Tracker",
        "startDate": "2019",
        "description": "Personal project for expenses tracker",
        "images": [
          "images/portfolio/expenses-tracker/p1.png",
          "images/portfolio/expenses-tracker/p2.png"
        ],
        "url": "https://github.com",
        "technologies": [
          {
            "class": "devicon-vuejs-plain",
            "name": "Vue"
          },
          {
            "class": "devicon-javascript-plain",
            "name": "JavaScript"
          },
          {
            "class": "devicon-python-plain",
            "name": "Python"
          }
        ]
      },
      {
        "title": "JMBooks",
        "startDate": "2018",
        "description": "One of the first project I was working in school.",
        "images": [
          "images/portfolio/jmbooks/p1.png",
          "images/portfolio/jmbooks/p1.png"
        ],
        "url": "https://github.com",
        "technologies": [
          {
            "class": "devicon-php-plain",
            "name": "Php"
          },
          {
            "class": "devicon-mysql-plain",
            "name": "MySQL"
          }
        ]
      }
    ],
    "experience": [
      {
        "company": "Netpolaris S.R.L.",
        "title": "Full Stack Developer",
        "years": "09.2019 - today",
        "mainTech": [
          "Java"
        ],
        "technologies": [
          "Java",
          "JavaScript",
          "Bootstrap",
          "MySQL",
          "Python",
          "REST API"
        ]
      }
    ]
  }